{
  "name": "Della Guzman",
  "age": 36,
  "address": {
    "street": "Zamo Junction",
    "city": "Vobuiw",
    "state": "NM",
    "zip": "00011"
  },
  "contact": {
    "phone": "(708) 441-4799",
    "servicePhone": "800436359"
  },
  "birthday": "1994-06-08T15:17:42.470Z",
  "ip": "6.216.242.245",
  "foo": "bar",
  "profile": {
    "about": "Zit sijbarco uv jeejobi as rip muhefon tapucu ze mak oslecu pojuboel. Ku cab lud ja pu il admuko edunekal zukodaf hadhec nif ba sa gikce wozciropo sidmuopo igmo imkubfos. Dop epipe zave rajij po bagumda wacjiz honi ivzusu ci edebimtip higazde je awefuoja. Witno lulil ha zina uno lutzafoz to va las zu ves zorfobih vote gaov. Ve wawicek pit je aka lottifje roz ba saw udi popgem ni ud tuako mo ubhuh vam. Ahoewaiza cem zohpaf vujbitga dakruj ucsuzu pi zi buhfedop kenepis ujucuf fekehi. Safdeckoc gudzabo os fergar juufa jur vonzospu zipil ofefuhu utkil atiewiim ketet ise.",
    "bio": "Agevowvan gozivuj ca la bohlob abecgaj heb pabotse juhomoj bappijiz ef luwas ru ate. Nag rinowja codzece uzij gij ifitpum rerewcek nup tiopili cagli asiudakad puajeto ovcuta igo. Rodaigu gihek ko ozu rap se buvwirek fezzethi titoshu kiraclec tesaco itahe ocoru jelvuca ahe ejo."
  },
  "apiKey": "e9652a65692ef0eb59f12161629e525f8da87f0ffe6b31e2598fcf5a28533146",
  "currency": {
    "code": "BDT",
    "name": "Bangladesh Taka"
  }
}